commandio/__init__.py
commandio/command.py
commandio/enums.py
commandio/fileio.py
commandio/iobase.py
commandio/logutil.py
commandio/tmpdir.py
commandio/tmpfile.py
commandio/util.py
commandio/workdir.py
commandio/misc/version.txt
commandio-0.0.1a1.dist-info/LICENSE
commandio-0.0.1a1.dist-info/METADATA
commandio-0.0.1a1.dist-info/WHEEL
commandio-0.0.1a1.dist-info/top_level.txt
commandio-0.0.1a1.dist-info/RECORD
