Metadata-Version: 2.1
Name: commandio
Version: 0.0.1a1
Summary: Python package that logs and executes commands for the command line.
Home-page: https://github.com/AdebayoBraimah/commandio
Author: Adebayo Braimah
Author-email: adebayo.braimah@gmail.com
License: GPL-3.0 License
Keywords: Command line shell UNIX Windows
Platform: UNKNOWN
Classifier: Natural Language :: English
Classifier: Operating System :: OS Independent
Classifier: Programming Language :: Python :: 3
Classifier: License :: OSI Approved :: GNU General Public License v3 (GPLv3)
Classifier: Programming Language :: Python :: 3 :: Only
Classifier: Topic :: System :: Software Distribution
Classifier: Topic :: Utilities
Requires-Python: >=3.7
